fastembed_bio/__init__.py
fastembed_bio/bio/__init__.py
fastembed_bio/bio/protein_embedding.py
fastembed_bio/common/__init__.py
fastembed_bio/common/model_description.py
fastembed_bio/common/model_management.py
fastembed_bio/common/onnx_model.py
fastembed_bio/common/preprocessor_utils.py
fastembed_bio/common/types.py
fastembed_bio/common/utils.py
fastembed_bio/parallel_processor.py
fastembed_bio/py.typed
fastembed_bio-0.1.2.dist-info/METADATA
fastembed_bio-0.1.2.dist-info/WHEEL
fastembed_bio-0.1.2.dist-info/licenses/LICENSE
fastembed_bio-0.1.2.dist-info/licenses/NOTICE
fastembed_bio-0.1.2.dist-info/RECORD
