Metadata-Version: 2.4
Name: fastembed-bio
Version: 0.1.2
Summary: Fast, light, accurate library for biological sequence embeddings (proteins, DNA, RNA)
License: Apache License
License-File: LICENSE
License-File: NOTICE
Keywords: vector,embedding,protein,esm2,bioinformatics,onnx,biological-sequences
Author: Nathan LeRoy
Author-email: nathanjleroy@gmail.com
Requires-Python: >=3.10.0
Classifier: License :: Other/Proprietary License
Classifier: Programming Language :: Python :: 3
Classifier: Programming Language :: Python :: 3.10
Classifier: Programming Language :: Python :: 3.11
Classifier: Programming Language :: Python :: 3.12
Classifier: Programming Language :: Python :: 3.13
Classifier: Programming Language :: Python :: 3.14
Requires-Dist: huggingface-hub (>=0.20,<2.0)
Requires-Dist: loguru (>=0.7.2,<0.8.0)
Requires-Dist: mmh3 (>=4.1.0,<6.0.0)
Requires-Dist: numpy (>=1.21) ; python_version == "3.11"
Requires-Dist: numpy (>=1.21,<2.3.0) ; python_version == "3.10"
Requires-Dist: numpy (>=1.26) ; python_version == "3.12"
Requires-Dist: numpy (>=2.1.0) ; python_version == "3.13"
Requires-Dist: numpy (>=2.3.0) ; python_version >= "3.14"
Requires-Dist: onnxruntime (>1.20.0) ; python_version >= "3.13"
Requires-Dist: onnxruntime (>=1.17.0,!=1.20.0) ; python_version >= "3.10" and python_version < "3.13"
Requires-Dist: py-rust-stemmers (>=0.1.0,<0.2.0)
Requires-Dist: requests (>=2.31,<3.0)
Requires-Dist: tokenizers (>=0.15,<1.0)
Requires-Dist: tqdm (>=4.66,<5.0)
Project-URL: Homepage, https://github.com/nleroy917/fastembed-bio
Project-URL: Repository, https://github.com/nleroy917/fastembed-bio
